cli/__init__.py
cli/command/__init__.py
cli/command/catalog_roles.py
cli/command/catalogs.py
cli/command/namespaces.py
cli/command/principal_roles.py
cli/command/principals.py
cli/command/privileges.py
cli/command/profiles.py
cli/constants.py
cli/options/__init__.py
cli/options/option_tree.py
cli/options/parser.py
cli/polaris_cli.py
polaris/.keep
polaris/__init__.py
polaris/catalog/.keep
polaris/catalog/__init__.py
polaris/catalog/api/.keep
polaris/catalog/api/__init__.py
polaris/catalog/api/catalog_api.py
polaris/catalog/api/configuration_api.py
polaris/catalog/api/generic_table_api.py
polaris/catalog/api/iceberg_catalog_api.py
polaris/catalog/api/iceberg_configuration_api.py
polaris/catalog/api/iceberg_o_auth2_api.py
polaris/catalog/api/o_auth2_api.py
polaris/catalog/api/policy_api.py
polaris/catalog/api_client.py
polaris/catalog/api_response.py
polaris/catalog/configuration.py
polaris/catalog/exceptions.py
polaris/catalog/models/.keep
polaris/catalog/models/__init__.py
polaris/catalog/models/add_partition_spec_update.py
polaris/catalog/models/add_schema_update.py
polaris/catalog/models/add_snapshot_update.py
polaris/catalog/models/add_sort_order_update.py
polaris/catalog/models/add_view_version_update.py
polaris/catalog/models/and_or_expression.py
polaris/catalog/models/applicable_policy.py
polaris/catalog/models/assert_create.py
polaris/catalog/models/assert_current_schema_id.py
polaris/catalog/models/assert_default_sort_order_id.py
polaris/catalog/models/assert_default_spec_id.py
polaris/catalog/models/assert_last_assigned_field_id.py
polaris/catalog/models/assert_last_assigned_partition_id.py
polaris/catalog/models/assert_ref_snapshot_id.py
polaris/catalog/models/assert_table_uuid.py
polaris/catalog/models/assert_view_uuid.py
polaris/catalog/models/assign_uuid_update.py
polaris/catalog/models/async_planning_result.py
polaris/catalog/models/attach_policy_request.py
polaris/catalog/models/base_update.py
polaris/catalog/models/blob_metadata.py
redpanda_polaris_catalog_python-1.0.0.post3.dist-info/METADATA
redpanda_polaris_catalog_python-1.0.0.post3.dist-info/WHEEL
redpanda_polaris_catalog_python-1.0.0.post3.dist-info/entry_points.txt
redpanda_polaris_catalog_python-1.0.0.post3.dist-info/RECORD
