Metadata-Version: 2.3
Name: redpanda-polaris-catalog-python
Version: 1.0.0.post3
Summary: Apache Polaris
License: Apache-2.0
Keywords: Apache Polaris,Polaris,Polaris Management Service,Apache Iceberg REST Catalog API
Author: Apache Software Foundation
Author-email: dev@polaris.apache.org
Requires-Python: >=3.9,<4.0
Classifier: License :: OSI Approved :: Apache Software License
Classifier: Programming Language :: Python :: 3
Classifier: Programming Language :: Python :: 3.9
Classifier: Programming Language :: Python :: 3.10
Classifier: Programming Language :: Python :: 3.11
Classifier: Programming Language :: Python :: 3.12
Classifier: Programming Language :: Python :: 3.13
Requires-Dist: boto3 (>=1.40.2)
Requires-Dist: pydantic (>=2.0.0)
Requires-Dist: python-dateutil (>=2.8.2)
Requires-Dist: typing-extensions (>=4.7.1)
Requires-Dist: urllib3 (>=1.25.3,<3.0.0)
Project-URL: Homepage, https://polaris.apache.org/
Project-URL: Repository, https://github.com/apache/polaris/
